agent_framework/__init__.py
agent_framework/_agents.py
agent_framework/_clients.py
agent_framework/_logging.py
agent_framework/_mcp.py
agent_framework/_memory.py
agent_framework/_middleware.py
agent_framework/_pydantic.py
agent_framework/_serialization.py
agent_framework/_telemetry.py
agent_framework/_threads.py
agent_framework/_tools.py
agent_framework/_types.py
agent_framework/exceptions.py
agent_framework/observability.py
agent_framework/py.typed
agent_framework/_workflows/README.md
agent_framework/_workflows/__init__.py
agent_framework/_workflows/_agent.py
agent_framework/_workflows/_agent_executor.py
agent_framework/_workflows/_agent_utils.py
agent_framework/_workflows/_base_group_chat_orchestrator.py
agent_framework/_workflows/_checkpoint.py
agent_framework/_workflows/_checkpoint_encoding.py
agent_framework/_workflows/_checkpoint_summary.py
agent_framework/_workflows/_concurrent.py
agent_framework/_workflows/_const.py
agent_framework/_workflows/_conversation_history.py
agent_framework/_workflows/_conversation_state.py
agent_framework/_workflows/_edge.py
agent_framework/_workflows/_edge_runner.py
agent_framework/_workflows/_events.py
agent_framework/_workflows/_exceptions.py
agent_framework/_workflows/_executor.py
agent_framework/_workflows/_function_executor.py
agent_framework/_workflows/_group_chat.py
agent_framework/_workflows/_handoff.py
agent_framework/_workflows/_magentic.py
agent_framework/_workflows/_message_utils.py
agent_framework/_workflows/_model_utils.py
agent_framework/_workflows/_orchestration_request_info.py
agent_framework/_workflows/_orchestration_state.py
agent_framework/_workflows/_orchestrator_helpers.py
agent_framework/_workflows/_request_info_mixin.py
agent_framework/_workflows/_runner.py
agent_framework/_workflows/_runner_context.py
agent_framework/_workflows/_sequential.py
agent_framework/_workflows/_shared_state.py
agent_framework/_workflows/_typing_utils.py
agent_framework/_workflows/_validation.py
agent_framework/_workflows/_viz.py
agent_framework_core-1.0.0b260114.dist-info/licenses/LICENSE
agent_framework_core-1.0.0b260114.dist-info/WHEEL
agent_framework_core-1.0.0b260114.dist-info/METADATA
agent_framework_core-1.0.0b260114.dist-info/RECORD
