Metadata-Version: 2.4
Name: agent-framework-core
Version: 1.0.0b260114
Summary: Microsoft Agent Framework for building AI Agents with Python. This is the core package that has all the core abstractions and implementations.
Author-email: Microsoft <af-support@microsoft.com>
Requires-Python: >=3.10
Classifier: License :: OSI Approved :: MIT License
Classifier: Development Status :: 4 - Beta
Classifier: Intended Audience :: Developers
Classifier: Programming Language :: Python :: 3
Classifier: Programming Language :: Python :: 3.10
Classifier: Programming Language :: Python :: 3.11
Classifier: Programming Language :: Python :: 3.12
Classifier: Programming Language :: Python :: 3.13
Classifier: Programming Language :: Python :: 3.14
Classifier: Typing :: Typed
License-File: LICENSE
Requires-Dist: typing-extensions
Requires-Dist: pydantic>=2,<3
Requires-Dist: pydantic-settings>=2,<3
Requires-Dist: opentelemetry-api>=1.39.0
Requires-Dist: opentelemetry-sdk>=1.39.0
Requires-Dist: opentelemetry-semantic-conventions-ai>=0.4.13
Requires-Dist: openai>=1.99.0
Requires-Dist: azure-identity>=1,<2
Requires-Dist: mcp[ws]>=1.24.0,<2
Requires-Dist: packaging>=24.1
Requires-Dist: agent-framework-a2a ; extra == "all"
Requires-Dist: agent-framework-ag-ui ; extra == "all"
Requires-Dist: agent-framework-azure-ai-search ; extra == "all"
Requires-Dist: agent-framework-anthropic ; extra == "all"
Requires-Dist: agent-framework-azure-ai ; extra == "all"
Requires-Dist: agent-framework-azurefunctions ; extra == "all"
Requires-Dist: agent-framework-chatkit ; extra == "all"
Requires-Dist: agent-framework-copilotstudio ; extra == "all"
Requires-Dist: agent-framework-declarative ; extra == "all"
Requires-Dist: agent-framework-devui ; extra == "all"
Requires-Dist: agent-framework-lab ; extra == "all"
Requires-Dist: agent-framework-mem0 ; extra == "all"
Requires-Dist: agent-framework-ollama ; extra == "all"
Requires-Dist: agent-framework-purview ; extra == "all"
Requires-Dist: agent-framework-redis ; extra == "all"
Project-URL: homepage, https://aka.ms/agent-framework
Project-URL: issues, https://github.com/microsoft/agent-framework/issues
Project-URL: release_notes, https://github.com/microsoft/agent-framework/releases?q=tag%3Apython-1&expanded=true
Project-URL: source, https://github.com/microsoft/agent-framework/tree/main/python
Provides-Extra: all
